more_streamtools/__init__.py
sicp_streams/__init__.py
streamdemo/__init__.py
streamtools/__init__.py
sicp_streams-0.2.0.dist-info/LICENSE
sicp_streams-0.2.0.dist-info/WHEEL
sicp_streams-0.2.0.dist-info/METADATA
sicp_streams-0.2.0.dist-info/RECORD
