Metadata-Version: 2.1
Name: sicp-streams
Version: 0.2.0
Summary: Replace iterator with stream and enjoy immutable. 
Home-page: https://github.com/no1xsyzy/sicp-streams
License: MIT
Author: Xu Siyuan
Author-email: inqb@protonmail.com
Requires-Python: >=3.7,<4.0
Classifier: License :: OSI Approved :: MIT License
Classifier: Programming Language :: Python :: 3
Classifier: Programming Language :: Python :: 3.7
Classifier: Programming Language :: Python :: 3.8
Classifier: Programming Language :: Python :: 3.9
Classifier: Topic :: Education
Project-URL: Repository, https://github.com/no1xsyzy/sicp-streams
